manychrome/__init__.py
manychrome/colorful.py
manychrome/component.py
manychrome/findme.py
manychrome/happy_helpers.py
manychrome/manychrome_examples.py
manychrome/stylish.py
manychrome-0.1.0.dist-info/LICENSE
manychrome-0.1.0.dist-info/METADATA
manychrome-0.1.0.dist-info/WHEEL
manychrome-0.1.0.dist-info/top_level.txt
manychrome-0.1.0.dist-info/RECORD
