Metadata-Version: 2.1
Name: manychrome
Version: 0.1.0
Summary: A simple package to colour and style your text printed on the CLI.
Home-page: https://github.com/NeurosystemsCo/manychrome
Author: Maria Wenner
Author-email: mail@neurosystems.co
License: MIT License
Classifier: Programming Language :: Python :: 3
Classifier: Operating System :: MacOS
Requires-Python: >=3.8
License-File: LICENSE
